nginx_set_conf/__init__.py
nginx_set_conf/config_templates.py
nginx_set_conf/nginx_set_conf.py
nginx_set_conf/utils.py
nginx_set_conf_equitania-1.0.7.dist-info/LICENSE.txt
nginx_set_conf_equitania-1.0.7.dist-info/METADATA
nginx_set_conf_equitania-1.0.7.dist-info/WHEEL
nginx_set_conf_equitania-1.0.7.dist-info/entry_points.txt
nginx_set_conf_equitania-1.0.7.dist-info/top_level.txt
nginx_set_conf_equitania-1.0.7.dist-info/RECORD
