Metadata-Version: 2.1
Name: nginx-set-conf-equitania
Version: 1.0.7
Summary: A package to create configurations for nginx for different web applications
Author: Equitania Software GmbH
Author-email: info@equitania.de
Classifier: Programming Language :: Python :: 3
Classifier: License :: OSI Approved :: GNU Affero General Public License v3
Classifier: Operating System :: OS Independent
Requires-Python: >=3.8
License-File: LICENSE.txt
Requires-Dist: click >=8.0.4
Requires-Dist: PyYaml >=5.4.1
